{
  "delta:player_setup": {
    "criteria": {
      "requirement": "2023-07-13 01:42:32 +0000"
    },
    "done": true
  },
  "classes:root": {
    "criteria": {
      "warrior": "2023-07-13 01:42:32 +0000"
    },
    "done": true
  },
  "survival:root": {
    "criteria": {
      "warrior": "2023-07-13 01:42:32 +0000"
    },
    "done": true
  },
  "minecraft:recipes/transportation/mangrove_boat": {
    "criteria": {
      "in_water": "2023-07-13 01:45:44 +0000"
    },
    "done": true
  },
  "minecraft:recipes/transportation/cherry_boat": {
    "criteria": {
      "in_water": "2023-07-13 01:45:44 +0000"
    },
    "done": true
  },
  "minecraft:recipes/transportation/bamboo_raft": {
    "criteria": {
      "in_water": "2023-07-13 01:45:44 +0000"
    },
    "done": true
  },
  "minecraft:recipes/building_blocks/dye_red_bed": {
    "criteria": {
      "has_needed_dye": "2023-07-13 01:47:22 +0000"
    },
    "done": true
  },
  "minecraft:recipes/building_blocks/dye_red_wool": {
    "criteria": {
      "has_needed_dye": "2023-07-13 01:47:22 +0000"
    },
    "done": true
  },
  "minecraft:recipes/building_blocks/dye_red_carpet": {
    "criteria": {
      "has_needed_dye": "2023-07-13 01:47:22 +0000"
    },
    "done": true
  },
  "minecraft:recipes/building_blocks/dye_pink_wool": {
    "criteria": {
      "has_needed_dye": "2023-07-13 01:49:35 +0000"
    },
    "done": true
  },
  "minecraft:recipes/building_blocks/dye_pink_bed": {
    "criteria": {
      "has_needed_dye": "2023-07-13 01:49:35 +0000"
    },
    "done": true
  },
  "minecraft:recipes/building_blocks/dye_pink_carpet": {
    "criteria": {
      "has_needed_dye": "2023-07-13 01:49:35 +0000"
    },
    "done": true
  },
  "minecraft:recipes/building_blocks/dye_lime_wool": {
    "criteria": {
      "has_needed_dye": "2023-07-13 01:52:39 +0000"
    },
    "done": true
  },
  "minecraft:recipes/building_blocks/dye_white_carpet": {
    "criteria": {
      "has_needed_dye": "2023-07-13 01:52:39 +0000"
    },
    "done": true
  },
  "minecraft:recipes/building_blocks/dye_white_wool": {
    "criteria": {
      "has_needed_dye": "2023-07-13 01:52:39 +0000"
    },
    "done": true
  },
  "minecraft:recipes/building_blocks/dye_lime_bed": {
    "criteria": {
      "has_needed_dye": "2023-07-13 01:52:39 +0000"
    },
    "done": true
  },
  "minecraft:recipes/building_blocks/dye_white_bed": {
    "criteria": {
      "has_needed_dye": "2023-07-13 01:52:39 +0000"
    },
    "done": true
  },
  "minecraft:recipes/building_blocks/dye_lime_carpet": {
    "criteria": {
      "has_needed_dye": "2023-07-13 01:52:39 +0000"
    },
    "done": true
  },
  "minecraft:recipes/building_blocks/dye_yellow_carpet": {
    "criteria": {
      "has_needed_dye": "2023-07-13 01:53:19 +0000"
    },
    "done": true
  },
  "minecraft:recipes/building_blocks/dye_yellow_wool": {
    "criteria": {
      "has_needed_dye": "2023-07-13 01:53:19 +0000"
    },
    "done": true
  },
  "minecraft:recipes/building_blocks/dye_yellow_bed": {
    "criteria": {
      "has_needed_dye": "2023-07-13 01:53:19 +0000"
    },
    "done": true
  },
  "minecraft:recipes/building_blocks/dye_gray_carpet": {
    "criteria": {
      "has_needed_dye": "2023-07-13 02:17:09 +0000"
    },
    "done": true
  },
  "minecraft:recipes/building_blocks/dye_gray_wool": {
    "criteria": {
      "has_needed_dye": "2023-07-13 02:17:09 +0000"
    },
    "done": true
  },
  "minecraft:recipes/building_blocks/dye_gray_bed": {
    "criteria": {
      "has_needed_dye": "2023-07-13 02:17:09 +0000"
    },
    "done": true
  },
  "DataVersion": 3465
}